{
  "apiVersion": "1",
  "name": "b-blocks/hotspot-block",
  "title": "Hotspot Block",
  "description": "Hotspot Block allows you to add interactive hotspots to your images.",
  "category": "widgets",
  "keywords": ["hotspot block", "hotspot", "image"],
  "textdomain": "hotspot-block",
  "attributes": {
    "align": {
      "type": "string",
      "default": ""
    },
    "cId": {
      "type": "string",
      "default": ""
    },
    "content": {
      "type": "string",
      "default": ""
    },
    "image": {
      "type": "object",
      "default": {
        "url": "",
        "height": { "desktop": "400px", "tablet": "400px", "mobile": "400px" },
        "device": "desktop",
        "heightDevice": "desktop",
        "width": { "desktop": "100%", "tablet": "100%", "mobile": "100%" },
        "padding": {
          "desktop": {
            "left": "0px",
            "right": "0px",
            "top": "0px",
            "bottom": "0px"
          },
          "tablet": {
            "left": "0px",
            "right": "0px",
            "top": "0px",
            "bottom": "0px"
          },
          "mobile": {
            "left": "0px",
            "right": "0px",
            "top": "0px",
            "bottom": "0px"
          }
        },
        "paddingDesktop": {
          "left": "0px",
          "right": "0px",
          "top": "0px",
          "bottom": "0px"
        },
        "paddingTablet": {
          "left": "0px",
          "right": "0px",
          "top": "0px",
          "bottom": "0px"
        },
        "paddingMobile": {
          "left": "0px",
          "right": "0px",
          "top": "0px",
          "bottom": "0px"
        },
        "paddingDevice": "desktop",
        "customSize": "full",
        "borderRadius": { "desktop": "3px", "tablet": "3px", "mobile": "3px" },
        "borderRadiusDevice": "desktop",
        "border": "none",
        "borderColor": "#ccc",
        "borderWidth": { "desktop": "0px", "tablet": "0px", "mobile": "0px" },
        "borderWidthDevice": "desktop",
        "boxShadow": "0px 0px 0px 0px #707070"
      }
    },
    "options": {
      "type": "object",
      "default": {
        "speed": 400,
        "delay": 200
      }
    },
    "preset": {
      "type": "number",
      "default": 1
    },
    "spotsone": {
      "type": "object",
      "default": {
        "bgColor": "#8a2be2",
        "borderColor": "",
        "height": { "desktop": "40px", "tablet": "40px", "mobile": "40px" },
        "heightDevice": "desktop",
        "width": { "desktop": "40px", "tablet": "40px", "mobile": "40px" },
        "widthDevice": "desktop",
        "padding": {
          "desktop": {
            "left": "0px",
            "right": "0px",
            "top": "0px",
            "bottom": "0px"
          },
          "tablet": {
            "left": "0px",
            "right": "0px",
            "top": "0px",
            "bottom": "0px"
          },
          "mobile": {
            "left": "0px",
            "right": "0px",
            "top": "0px",
            "bottom": "0px"
          }
        },
        "paddingDevice": "desktop",
        "borderRadius": {
          "desktop": {
            "left": "50px",
            "right": "50px",
            "top": "50px",
            "bottom": "50px"
          },
          "tablet": {
            "left": "50px",
            "right": "50px",
            "top": "50px",
            "bottom": "50px"
          },
          "mobile": {
            "left": "50px",
            "right": "50px",
            "top": "50px",
            "bottom": "50px"
          }
        },
        "borderRadiusDevice": "desktop",
        "borderWidth": {
          "desktop": "0px",
          "tablet": "0px",
          "mobile": "0px"
        },
        "borderWidthDevice": "desktop",
        "iconColor": "#fff",
        "iconSize": { "desktop": "12px", "tablet": "12px", "mobile": "12px" },
        "iconSizeDevice": "desktop",
        "borderType": "none",
        "hover": "normal",
        "hoverColor": { "icon": "#fff", "bg": "", "border": "" }
      }
    },
    "tooltipone": {
      "type": "object",
      "default": {
        "width": "200px",
        "padding": {
          "desktop": {
            "left": "5px",
            "right": "5px",
            "top": "5px",
            "bottom": "5px"
          },
          "tablet": {
            "left": "5px",
            "right": "5px",
            "top": "5px",
            "bottom": "5px"
          },
          "mobile": {
            "left": "5px",
            "right": "5px",
            "top": "5px",
            "bottom": "5px"
          }
        },
        "paddingDevice": "desktop",
        "borderRadius": {
          "desktop": {
            "left": "3px",
            "right": "3px",
            "top": "3px",
            "bottom": "3px"
          },
          "tablet": {
            "left": "3px",
            "right": "3px",
            "top": "3px",
            "bottom": "3px"
          },
          "mobile": {
            "left": "3px",
            "right": "3px",
            "top": "3px",
            "bottom": "3px"
          }
        },
        "borderRadiusDevice": "desktop",
        "borderColor": "#fff",
        "borderWidth": "0px",
        "textColor": "#fff",
        "bgColor": "#8a2be2",
        "boxShadow": "0px 0px 0px 0px #707070"
      }
    },
    "themeone": {
      "type": "array",
      "default": [
        {
          "borderColor": "",
          "bgColor": "",
          "spotsSize": "",
          "isDragging": false,
          "option": "spot",
          "spotOption": 1,
          "spotText": "+",
          "icon": "",
          "image": "",
          "tooltip": "<p>Tooltip contents</p>",
          "tooltipPosition": "left",
          "position": {
            "x": 0,
            "y": 0
          },
          "iconColor": "",
          "iconSize": "12px",
          "spotLink": "",
          "newWindow": false
        },
        {
          "borderColor": "",
          "bgColor": "",
          "spotsSize": "",
          "option": "spot",
          "spotOption": 1,
          "spotText": "+",
          "icon": "",
          "image": "",
          "tooltip": "<p>Tooltip contents</p>",
          "tooltipPosition": "left",
          "position": {
            "x": 100,
            "y": 100
          },
          "iconColor": "",
          "iconSize": "12px",
          "spotLink": "",
          "newWindow": false
        }
      ]
    }
  },
  "supports": {
    "align": ["wide", "full"],
    "html": false
  },
  "example": {
    "attributes": {
      "preview": true,
      "columns": {
        "desktop": 1,
        "tablet": 1,
        "mobile": 1
      }
    }
  },
  "editorScript": "file:./../dist/editor.js"
}
